[{"id":108,"user_site_id":1,"user_site_object_id":98,"action_taken_at_time":"2014-04-07T12:21:59Z","sync_object_action_id":6,"sync_object_type_id":1,"sync_object_id":5823,"sync_object_site_id":1,"parameters":[{"created_at":"2014-04-07T12:21:59Z","id":556,"param_object_id":null,"param_object_site_id":null,"param_object_type_id":null,"parameter":"command","peer_log_id":108,"updated_at":"2014-04-07T12:21:59Z","value":"copy"},{"created_at":"2014-04-07T12:21:59Z","id":557,"param_object_id":null,"param_object_site_id":null,"param_object_type_id":null,"parameter":"item_count","peer_log_id":108,"updated_at":"2014-04-07T12:21:59Z","value":"2"},{"created_at":"2014-04-07T12:21:59Z","id":558,"param_object_id":null,"param_object_site_id":null,"param_object_type_id":null,"parameter":"all_items","peer_log_id":108,"updated_at":"2014-04-07T12:21:59Z","value":"0"},{"created_at":"2014-04-07T12:21:59Z","id":559,"param_object_id":null,"param_object_site_id":null,"param_object_type_id":null,"parameter":"overwrite","peer_log_id":108,"updated_at":"2014-04-07T12:21:59Z","value":"0"},{"created_at":"2014-04-07T12:21:59Z","id":560,"param_object_id":null,"param_object_site_id":null,"param_object_type_id":null,"parameter":"copied_collections_origin_ids","peer_log_id":108,"updated_at":"2014-04-07T12:21:59Z","value":"5824,,"},{"created_at":"2014-04-07T12:21:59Z","id":561,"param_object_id":null,"param_object_site_id":null,"param_object_type_id":null,"parameter":"copied_collections_site_ids","peer_log_id":108,"updated_at":"2014-04-07T12:21:59Z","value":"1,,"},{"created_at":"2014-04-07T12:21:59Z","id":562,"param_object_id":null,"param_object_site_id":null,"param_object_type_id":null,"parameter":"collection_items_origin_ids","peer_log_id":108,"updated_at":"2014-04-07T12:21:59Z","value":"169,"},{"created_at":"2014-04-07T12:21:59Z","id":563,"param_object_id":null,"param_object_site_id":null,"param_object_type_id":null,"parameter":"collection_items_site_ids","peer_log_id":108,"updated_at":"2014-04-07T12:21:59Z","value":"1,"},{"created_at":"2014-04-07T12:21:59Z","id":564,"param_object_id":null,"param_object_site_id":null,"param_object_type_id":null,"parameter":"collection_items_names","peer_log_id":108,"updated_at":"2014-04-07T12:21:59Z","value":""},{"created_at":"2014-04-07T12:21:59Z","id":565,"param_object_id":null,"param_object_site_id":null,"param_object_type_id":null,"parameter":"collection_items_types","peer_log_id":108,"updated_at":"2014-04-07T12:21:59Z","value":"TaxonConcept,"}],"object_type":"Collection","object_action":"create_job"},{"id":109,"user_site_id":1,"user_site_object_id":98,"action_taken_at_time":"2014-04-07T12:22:04Z","sync_object_action_id":1,"sync_object_type_id":1,"sync_object_id":169,"sync_object_site_id":1,"parameters":[{"created_at":"2014-04-07T12:22:04Z","id":566,"param_object_id":null,"param_object_site_id":null,"param_object_type_id":null,"parameter":"collected_item_name","peer_log_id":109,"updated_at":"2014-04-07T12:22:04Z","value":null},{"created_at":"2014-04-07T12:22:04Z","id":567,"param_object_id":null,"param_object_site_id":null,"param_object_type_id":null,"parameter":"collected_item_type","peer_log_id":109,"updated_at":"2014-04-07T12:22:04Z","value":null},{"created_at":"2014-04-07T12:22:04Z","id":568,"param_object_id":null,"param_object_site_id":null,"param_object_type_id":null,"parameter":"item_id","peer_log_id":109,"updated_at":"2014-04-07T12:22:04Z","value":"10"},{"created_at":"2014-04-07T12:22:04Z","id":569,"param_object_id":null,"param_object_site_id":null,"param_object_type_id":null,"parameter":"item_site_id","peer_log_id":109,"updated_at":"2014-04-07T12:22:04Z","value":"1"}],"object_type":"Collection","object_action":"add_item"}]