[{"id":320,"user_site_id":1,"user_site_object_id":98,"action_taken_at_time":"2014-04-16T09:47:36Z","sync_object_action_id":1,"sync_object_type_id":4,"sync_object_id":259,"sync_object_site_id":2,"parameters":[{"created_at":"2014-04-16T09:47:36Z","id":1887,"param_object_id":null,"param_object_site_id":null,"param_object_type_id":null,"parameter":"from_curator","peer_log_id":320,"updated_at":"2014-04-16T09:47:36Z","value":"0"},{"created_at":"2014-04-16T09:47:36Z","id":1888,"param_object_id":null,"param_object_site_id":null,"param_object_type_id":null,"parameter":"visible_at","peer_log_id":320,"updated_at":"2014-04-16T09:47:36Z","value":"2014-04-16 09:47:35"},{"created_at":"2014-04-16T09:47:36Z","id":1889,"param_object_id":null,"param_object_site_id":null,"param_object_type_id":null,"parameter":"hidden","peer_log_id":320,"updated_at":"2014-04-16T09:47:36Z","value":"0"},{"created_at":"2014-04-16T09:47:37Z","id":1890,"param_object_id":null,"param_object_site_id":null,"param_object_type_id":null,"parameter":"comment_parent_origin_id","peer_log_id":320,"updated_at":"2014-04-16T09:47:37Z","value":"5853"},{"created_at":"2014-04-16T09:47:37Z","id":1891,"param_object_id":null,"param_object_site_id":null,"param_object_type_id":null,"parameter":"comment_parent_site_id","peer_log_id":320,"updated_at":"2014-04-16T09:47:37Z","value":"1"},{"created_at":"2014-04-16T09:47:37Z","id":1892,"param_object_id":null,"param_object_site_id":null,"param_object_type_id":null,"parameter":"parent_type","peer_log_id":320,"updated_at":"2014-04-16T09:47:37Z","value":"Collection"},{"created_at":"2014-04-16T09:47:37Z","id":1893,"param_object_id":null,"param_object_site_id":null,"param_object_type_id":null,"parameter":"reply_to_type","peer_log_id":320,"updated_at":"2014-04-16T09:47:37Z","value":""},{"created_at":"2014-04-16T09:47:37Z","id":1894,"param_object_id":null,"param_object_site_id":null,"param_object_type_id":null,"parameter":"reply_to_id","peer_log_id":320,"updated_at":"2014-04-16T09:47:37Z","value":""},{"created_at":"2014-04-16T09:47:37Z","id":1895,"param_object_id":null,"param_object_site_id":null,"param_object_type_id":null,"parameter":"body","peer_log_id":320,"updated_at":"2014-04-16T09:47:37Z","value":"local comment change"}],"object_type":"Comment","object_action":"create"}]