[{"id":352,"user_site_id":1,"user_site_object_id":98,"action_taken_at_time":"2014-04-27T08:25:42Z","sync_object_action_id":2,"sync_object_type_id":5,"sync_object_id":null,"sync_object_site_id":null,"parameters":[{"created_at":"2014-04-27T08:25:42Z","id":1934,"param_object_id":null,"param_object_site_id":null,"param_object_type_id":null,"parameter":"reference","peer_log_id":352,"updated_at":"2014-04-27T08:25:42Z","value":"wow5"}],"object_type":"Ref","object_action":"create"},{"id":353,"user_site_id":1,"user_site_object_id":98,"action_taken_at_time":"2014-04-27T08:25:42Z","sync_object_action_id":7,"sync_object_type_id":6,"sync_object_id":5853,"sync_object_site_id":1,"parameters":[{"created_at":"2014-04-27T08:25:42Z","id":1935,"param_object_id":null,"param_object_site_id":null,"param_object_type_id":null,"parameter":"collected_item_type","peer_log_id":353,"updated_at":"2014-04-27T08:25:42Z","value":"TaxonConcept"},{"created_at":"2014-04-27T08:25:42Z","id":1936,"param_object_id":null,"param_object_site_id":null,"param_object_type_id":null,"parameter":"item_id","peer_log_id":353,"updated_at":"2014-04-27T08:25:42Z","value":"18"},{"created_at":"2014-04-27T08:25:42Z","id":1937,"param_object_id":null,"param_object_site_id":null,"param_object_type_id":null,"parameter":"item_site_id","peer_log_id":353,"updated_at":"2014-04-27T08:25:42Z","value":"1"},{"created_at":"2014-04-27T08:25:42Z","id":1938,"param_object_id":null,"param_object_site_id":null,"param_object_type_id":null,"parameter":"annotation","peer_log_id":353,"updated_at":"2014-04-27T08:25:42Z","value":"try update col item last"},{"created_at":"2014-04-27T08:25:42Z","id":1939,"param_object_id":null,"param_object_site_id":null,"param_object_type_id":null,"parameter":"sort_field","peer_log_id":353,"updated_at":"2014-04-27T08:25:42Z","value":""},{"created_at":"2014-04-27T08:25:42Z","id":1940,"param_object_id":null,"param_object_site_id":null,"param_object_type_id":null,"parameter":"references","peer_log_id":353,"updated_at":"2014-04-27T08:25:42Z","value":"---\n- wow5\n"}],"object_type":"collection_item","object_action":"update"}]