[{"id":14,"user_site_id":1,"user_site_object_id":98,"action_taken_at_time":"2014-03-25T13:15:46Z","sync_object_action_id":1,"sync_object_type_id":1,"sync_object_id":98,"sync_object_site_id":1,"parameters":[{"created_at":"2014-03-25T13:15:46Z","id":196,"param_object_id":null,"param_object_site_id":null,"param_object_type_id":null,"parameter":"updated_at","peer_log_id":14,"updated_at":"2014-03-25T13:15:46Z","value":"2014-03-25 13:15:46"},{"created_at":"2014-03-25T13:15:46Z","id":197,"param_object_id":null,"param_object_site_id":null,"param_object_type_id":null,"parameter":"api_key","peer_log_id":14,"updated_at":"2014-03-25T13:15:46Z","value":null},{"created_at":"2014-03-25T13:15:46Z","id":198,"param_object_id":null,"param_object_site_id":null,"param_object_type_id":null,"parameter":"curator_level_id","peer_log_id":14,"updated_at":"2014-03-25T13:15:46Z","value":null},{"created_at":"2014-03-25T13:15:46Z","id":199,"param_object_id":null,"param_object_site_id":null,"param_object_type_id":null,"parameter":"logo_cache_url","peer_log_id":14,"updated_at":"2014-03-25T13:15:46Z","value":"201403250903470"},{"created_at":"2014-03-25T13:15:47Z","id":200,"param_object_id":null,"param_object_site_id":null,"param_object_type_id":null,"parameter":"logo_file_name","peer_log_id":14,"updated_at":"2014-03-25T13:15:47Z","value":"400x400.jpg"},{"created_at":"2014-03-25T13:15:47Z","id":201,"param_object_id":null,"param_object_site_id":null,"param_object_type_id":null,"parameter":"logo_content_type","peer_log_id":14,"updated_at":"2014-03-25T13:15:47Z","value":"image/jpeg"},{"created_at":"2014-03-25T13:15:47Z","id":202,"param_object_id":null,"param_object_site_id":null,"param_object_type_id":null,"parameter":"logo_file_size","peer_log_id":14,"updated_at":"2014-03-25T13:15:47Z","value":"31370"},{"created_at":"2014-03-25T13:15:47Z","id":203,"param_object_id":null,"param_object_site_id":null,"param_object_type_id":null,"parameter":"base_url","peer_log_id":14,"updated_at":"2014-03-25T13:15:47Z","value":"http://localhost:80/eol_php_code/applications/content_server/content/"},{"created_at":"2014-03-25T13:15:47Z","id":204,"param_object_id":null,"param_object_site_id":null,"param_object_type_id":null,"parameter":"bio","peer_log_id":14,"updated_at":"2014-03-25T13:15:47Z","value":""},{"created_at":"2014-03-25T13:15:47Z","id":205,"param_object_id":null,"param_object_site_id":null,"param_object_type_id":null,"parameter":"given_name","peer_log_id":14,"updated_at":"2014-03-25T13:15:47Z","value":"userd"},{"created_at":"2014-03-25T13:15:47Z","id":206,"param_object_id":null,"param_object_site_id":null,"param_object_type_id":null,"parameter":"family_name","peer_log_id":14,"updated_at":"2014-03-25T13:15:47Z","value":"userdgggg"},{"created_at":"2014-03-25T13:15:47Z","id":207,"param_object_id":null,"param_object_site_id":null,"param_object_type_id":null,"parameter":"tag_line","peer_log_id":14,"updated_at":"2014-03-25T13:15:47Z","value":""},{"created_at":"2014-03-25T13:15:47Z","id":208,"param_object_id":null,"param_object_site_id":null,"param_object_type_id":null,"parameter":"user_identity_ids","peer_log_id":14,"updated_at":"2014-03-25T13:15:47Z","value":null},{"created_at":"2014-03-25T13:15:47Z","id":209,"param_object_id":null,"param_object_site_id":null,"param_object_type_id":null,"parameter":"username","peer_log_id":14,"updated_at":"2014-03-25T13:15:47Z","value":"userd"},{"created_at":"2014-03-25T13:15:47Z","id":210,"param_object_id":null,"param_object_site_id":null,"param_object_type_id":null,"parameter":"language_abbr","peer_log_id":14,"updated_at":"2014-03-25T13:15:47Z","value":"en"}],"object_type":"User","object_action":"update"}]